{"type": "FeatureCollection", "id": "http://pleiades.stoa.org/places/89318.0", "name": "89318.0", "features": [{"type": "Feature", "id": "http://data.archaeology.link/data/samian/loc_ds_1002808", "name": "Old Penrith", "dateprops": [], "properties": {"http://archaeology.link/ontology#exactMatch": ["http://www.wikidata.org/entity/Q103188158"], "http://archaeology.link/ontology#hasType": ["http://archaeology.link/ontology#DiscoverySite"], "http://archaeology.link/ontology#pleiadesID": ["89318.0", "http://pleiades.stoa.org/places/89318.0"], "http://purl.org/dc/elements/1.1/identifier": ["1002808"], "http://purl.org/dc/terms/subject": ["samian ware discovery site"], "http://purl.org/dc/terms/title": ["Old Penrith"], "http://www.opengis.net/ont/geosparql#hasGeometry": ["http://data.archaeology.link/data/samian/loc_ds_1002808_geom"], "http://www.w3.org/1999/02/22-rdf-syntax-ns#type": ["http://archaeology.link/ontology#Location", "http://archaeology.link/ontology#DiscoverySite", "http://pelagios.github.io/vocab/terms#AnnotatedThing"], "http://www.w3.org/2000/01/rdf-schema#label": ["Old Penrith"], "http://www.w3.org/ns/prov-o/wasAttributedTo": ["http://data.archaeology.link/data/samian/ImportPythonScript_Samian"], "http://www.w3.org/ns/prov-o/wasDerivedFrom": ["http://www.wikidata.org/entity/Q90412636"], "http://www.w3.org/ns/prov-o/wasGeneratedBy": ["http://data.archaeology.link/data/samian/activity_loc_ds_1002808"], "http://xmlns.com/foaf/0.1/homepage": ["<http://lod.archaeology.link/samian/>"]}, "geometry": {"type": "Point", "coordinates": [-2.792124, 54.734279], "crs": "4326"}}], "numberMatched": 1, "numberReturned": 1, "bbox": [-2.792124, 54.734279, -2.792124, 54.734279], "crs": "http://www.opengis.net/def/crs/EPSG/0/4326"}