{"type": "FeatureCollection", "id": "http://www.wikidata.org/entity/Q103160311", "name": "Q103160311", "features": [{"type": "Feature", "id": "http://data.archaeology.link/data/samian/loc_ds_1004272", "name": "Cupra Marittima", "dateprops": [], "properties": {"http://archaeology.link/ontology#ancientName": ["Cupra Maritima"], "http://archaeology.link/ontology#exactMatch": ["http://www.wikidata.org/entity/Q103160311"], "http://archaeology.link/ontology#hasType": ["http://archaeology.link/ontology#DiscoverySite"], "http://purl.org/dc/elements/1.1/identifier": ["1004272"], "http://www.opengis.net/ont/geosparql#hasGeometry": ["http://data.archaeology.link/data/samian/loc_ds_1004272_geom"], "http://www.w3.org/1999/02/22-rdf-syntax-ns#type": ["http://archaeology.link/ontology#Location", "http://archaeology.link/ontology#DiscoverySite"], "http://www.w3.org/2000/01/rdf-schema#label": ["Cupra Marittima"], "http://www.w3.org/ns/prov-o/wasAttributedTo": ["http://data.archaeology.link/data/samian/ImportPythonScript_Samian"], "http://www.w3.org/ns/prov-o/wasDerivedFrom": ["http://www.wikidata.org/entity/Q90412636"], "http://www.w3.org/ns/prov-o/wasGeneratedBy": ["http://data.archaeology.link/data/samian/activity_loc_ds_1004272"]}, "geometry": {"type": "Point", "coordinates": [13.87, 43.03], "crs": "4326"}}], "numberMatched": 1, "numberReturned": 1, "bbox": [13.87, 43.03, 13.87, 43.03], "crs": "http://www.opengis.net/def/crs/EPSG/0/4326"}