{"type": "FeatureCollection", "id": "http://www.wikidata.org/entity/Q103145290", "name": "Q103145290", "features": [{"type": "Feature", "id": "http://data.archaeology.link/data/samian/loc_ds_1004107", "name": "Bad Nauheim", "dateprops": [], "properties": {"http://archaeology.link/ontology#exactMatch": ["http://www.wikidata.org/entity/Q103145290"], "http://archaeology.link/ontology#hasType": ["http://archaeology.link/ontology#DiscoverySite"], "http://purl.org/dc/elements/1.1/identifier": ["1004107"], "http://www.opengis.net/ont/geosparql#hasGeometry": ["http://data.archaeology.link/data/samian/loc_ds_1004107_geom"], "http://www.w3.org/1999/02/22-rdf-syntax-ns#type": ["http://archaeology.link/ontology#Location", "http://archaeology.link/ontology#DiscoverySite"], "http://www.w3.org/2000/01/rdf-schema#label": ["Bad Nauheim"], "http://www.w3.org/ns/prov-o/wasAttributedTo": ["http://data.archaeology.link/data/samian/ImportPythonScript_Samian"], "http://www.w3.org/ns/prov-o/wasDerivedFrom": ["http://www.wikidata.org/entity/Q90412636"], "http://www.w3.org/ns/prov-o/wasGeneratedBy": ["http://data.archaeology.link/data/samian/activity_loc_ds_1004107"]}, "geometry": {"type": "Point", "coordinates": [8.73859, 50.36463], "crs": "4326"}}], "numberMatched": 1, "numberReturned": 1, "bbox": [8.73859, 50.36463, 8.73859, 50.36463], "crs": "http://www.opengis.net/def/crs/EPSG/0/4326"}