{"type": "FeatureCollection", "id": "http://www.wikidata.org/entity/Q103141154", "name": "Q103141154", "features": [{"type": "Feature", "id": "http://data.archaeology.link/data/samian/loc_ds_1001620", "name": "Amancey", "dateprops": [], "properties": {"http://archaeology.link/ontology#exactMatch": ["http://www.wikidata.org/entity/Q103141154"], "http://archaeology.link/ontology#hasType": ["http://archaeology.link/ontology#DiscoverySite"], "http://purl.org/dc/elements/1.1/identifier": ["1001620"], "http://www.opengis.net/ont/geosparql#hasGeometry": ["http://data.archaeology.link/data/samian/loc_ds_1001620_geom"], "http://www.w3.org/1999/02/22-rdf-syntax-ns#type": ["http://archaeology.link/ontology#Location", "http://archaeology.link/ontology#DiscoverySite"], "http://www.w3.org/2000/01/rdf-schema#label": ["Amancey"], "http://www.w3.org/ns/prov-o/wasAttributedTo": ["http://data.archaeology.link/data/samian/ImportPythonScript_Samian"], "http://www.w3.org/ns/prov-o/wasDerivedFrom": ["http://www.wikidata.org/entity/Q90412636"], "http://www.w3.org/ns/prov-o/wasGeneratedBy": ["http://data.archaeology.link/data/samian/activity_loc_ds_1001620"]}, "geometry": {"type": "Point", "coordinates": [6.083333, 47.033332], "crs": "4326"}}], "numberMatched": 1, "numberReturned": 1, "bbox": [6.083333, 47.033332, 6.083333, 47.033332], "crs": "http://www.opengis.net/def/crs/EPSG/0/4326"}