{"type": "FeatureCollection", "id": "http://www.wikidata.org/entity/Q103163801", "name": "Q103163801", "features": [{"type": "Feature", "id": "http://data.archaeology.link/data/samian/loc_ds_1001822", "name": "Himera", "dateprops": [], "properties": {"http://archaeology.link/ontology#exactMatch": ["http://www.wikidata.org/entity/Q103163801"], "http://archaeology.link/ontology#hasType": ["http://archaeology.link/ontology#DiscoverySite"], "http://purl.org/dc/elements/1.1/identifier": ["1001822"], "http://www.opengis.net/ont/geosparql#hasGeometry": ["http://data.archaeology.link/data/samian/loc_ds_1001822_geom"], "http://www.w3.org/1999/02/22-rdf-syntax-ns#type": ["http://archaeology.link/ontology#Location", "http://archaeology.link/ontology#DiscoverySite"], "http://www.w3.org/2000/01/rdf-schema#label": ["Himera"], "http://www.w3.org/ns/prov-o/wasAttributedTo": ["http://data.archaeology.link/data/samian/ImportPythonScript_Samian"], "http://www.w3.org/ns/prov-o/wasDerivedFrom": ["http://www.wikidata.org/entity/Q90412636"], "http://www.w3.org/ns/prov-o/wasGeneratedBy": ["http://data.archaeology.link/data/samian/activity_loc_ds_1001822"]}, "geometry": {"type": "Point", "coordinates": [13.82, 37.96], "crs": "4326"}}], "numberMatched": 1, "numberReturned": 1, "bbox": [13.82, 37.96, 13.82, 37.96], "crs": "http://www.opengis.net/def/crs/EPSG/0/4326"}