{"type": "FeatureCollection", "id": "http://www.wikidata.org/entity/Q103161192", "name": "Q103161192", "features": [{"type": "Feature", "id": "http://data.archaeology.link/data/samian/loc_ds_1000706", "name": "Eisenberg", "dateprops": [], "properties": {"http://archaeology.link/ontology#exactMatch": ["http://www.wikidata.org/entity/Q103161192"], "http://archaeology.link/ontology#hasType": ["http://archaeology.link/ontology#DiscoverySite"], "http://purl.org/dc/elements/1.1/identifier": ["1000706"], "http://www.opengis.net/ont/geosparql#hasGeometry": ["http://data.archaeology.link/data/samian/loc_ds_1000706_geom"], "http://www.w3.org/1999/02/22-rdf-syntax-ns#type": ["http://archaeology.link/ontology#Location", "http://archaeology.link/ontology#DiscoverySite"], "http://www.w3.org/2000/01/rdf-schema#label": ["Eisenberg"], "http://www.w3.org/ns/prov-o/wasAttributedTo": ["http://data.archaeology.link/data/samian/ImportPythonScript_Samian"], "http://www.w3.org/ns/prov-o/wasDerivedFrom": ["http://www.wikidata.org/entity/Q90412636"], "http://www.w3.org/ns/prov-o/wasGeneratedBy": ["http://data.archaeology.link/data/samian/activity_loc_ds_1000706"]}, "geometry": {"type": "Point", "coordinates": [8.07, 49.565833], "crs": "4326"}}], "numberMatched": 1, "numberReturned": 1, "bbox": [8.07, 49.565833, 8.07, 49.565833], "crs": "http://www.opengis.net/def/crs/EPSG/0/4326"}