{"type": "FeatureCollection", "id": "http://www.wikidata.org/entity/Q103136235", "name": "Q103136235", "features": [{"type": "Feature", "id": "http://data.archaeology.link/data/samian/loc_pc_2000098", "name": "Venosa", "dateprops": [], "properties": {"http://academic-meta-tool.xyz/vocab#instanceOf": ["http://archaeology.link/ontology#Location"], "http://archaeology.link/ontology#exactMatch": ["http://www.wikidata.org/entity/Q103136235"], "http://archaeology.link/ontology#hasType": ["http://archaeology.link/ontology#ProductionCentre"], "http://purl.org/dc/elements/1.1/identifier": ["2000098"], "http://www.opengis.net/ont/geosparql#hasGeometry": ["http://data.archaeology.link/data/samian/loc_pc_2000098_geom"], "http://www.w3.org/1999/02/22-rdf-syntax-ns#type": ["http://archaeology.link/ontology#Location", "http://archaeology.link/ontology#ProductionCentre"], "http://www.w3.org/2000/01/rdf-schema#label": ["Venosa"], "http://www.w3.org/ns/prov-o/wasAttributedTo": ["http://data.archaeology.link/data/samian/ImportPythonScript_Samian"], "http://www.w3.org/ns/prov-o/wasDerivedFrom": ["http://www.wikidata.org/entity/Q90412636"], "http://www.w3.org/ns/prov-o/wasGeneratedBy": ["http://data.archaeology.link/data/samian/activity_loc_pc_2000098"]}, "geometry": {"type": "Point", "coordinates": [15.8166666, 40.9666672], "crs": "4326"}}], "numberMatched": 1, "numberReturned": 1, "bbox": [15.8166666, 40.9666672, 15.8166666, 40.9666672], "crs": "http://www.opengis.net/def/crs/EPSG/0/4326"}