{"type": "FeatureCollection", "id": "http://www.wikidata.org/entity/Q103173156", "name": "Q103173156", "features": [{"type": "Feature", "id": "http://data.archaeology.link/data/samian/loc_ds_1000766", "name": "Le Hallai", "dateprops": [], "properties": {"http://archaeology.link/ontology#exactMatch": ["http://www.wikidata.org/entity/Q103173156"], "http://archaeology.link/ontology#hasType": ["http://archaeology.link/ontology#DiscoverySite"], "http://purl.org/dc/elements/1.1/identifier": ["1000766"], "http://www.opengis.net/ont/geosparql#hasGeometry": ["http://data.archaeology.link/data/samian/loc_ds_1000766_geom"], "http://www.w3.org/1999/02/22-rdf-syntax-ns#type": ["http://archaeology.link/ontology#Location", "http://archaeology.link/ontology#DiscoverySite"], "http://www.w3.org/2000/01/rdf-schema#label": ["Le Hallai"], "http://www.w3.org/ns/prov-o/wasAttributedTo": ["http://data.archaeology.link/data/samian/ImportPythonScript_Samian"], "http://www.w3.org/ns/prov-o/wasDerivedFrom": ["http://www.wikidata.org/entity/Q90412636"], "http://www.w3.org/ns/prov-o/wasGeneratedBy": ["http://data.archaeology.link/data/samian/activity_loc_ds_1000766"]}, "geometry": {"type": "Point", "coordinates": [0.197222, 48.007778], "crs": "4326"}}], "numberMatched": 1, "numberReturned": 1, "bbox": [0.197222, 48.007778, 0.197222, 48.007778], "crs": "http://www.opengis.net/def/crs/EPSG/0/4326"}