{"type": "FeatureCollection", "id": "http://pleiades.stoa.org/places/79420.0", "name": "79420.0", "features": [{"type": "Feature", "id": "http://data.archaeology.link/data/samian/loc_ds_1002383", "name": "Chester", "dateprops": [], "properties": {"http://archaeology.link/ontology#ancientName": ["Deva Victrix"], "http://archaeology.link/ontology#exactMatch": ["http://www.wikidata.org/entity/Q103159527"], "http://archaeology.link/ontology#hasType": ["http://archaeology.link/ontology#DiscoverySite"], "http://archaeology.link/ontology#pleiadesID": ["79420.0", "http://pleiades.stoa.org/places/79420.0"], "http://purl.org/dc/elements/1.1/identifier": ["1002383"], "http://purl.org/dc/terms/subject": ["samian ware discovery site"], "http://purl.org/dc/terms/title": ["Chester"], "http://www.opengis.net/ont/geosparql#hasGeometry": ["http://data.archaeology.link/data/samian/loc_ds_1002383_geom"], "http://www.w3.org/1999/02/22-rdf-syntax-ns#type": ["http://archaeology.link/ontology#Location", "http://archaeology.link/ontology#DiscoverySite", "http://pelagios.github.io/vocab/terms#AnnotatedThing"], "http://www.w3.org/2000/01/rdf-schema#label": ["Chester"], "http://www.w3.org/ns/prov-o/wasAttributedTo": ["http://data.archaeology.link/data/samian/ImportPythonScript_Samian"], "http://www.w3.org/ns/prov-o/wasDerivedFrom": ["http://www.wikidata.org/entity/Q90412636"], "http://www.w3.org/ns/prov-o/wasGeneratedBy": ["http://data.archaeology.link/data/samian/activity_loc_ds_1002383"], "http://xmlns.com/foaf/0.1/homepage": ["<http://lod.archaeology.link/samian/>"]}, "geometry": {"type": "Point", "coordinates": [-2.892778, 53.191389], "crs": "4326"}}], "numberMatched": 1, "numberReturned": 1, "bbox": [-2.892778, 53.191389, -2.892778, 53.191389], "crs": "http://www.opengis.net/def/crs/EPSG/0/4326"}