{"type": "FeatureCollection", "id": "http://www.wikidata.org/entity/Q103162984", "name": "Q103162984", "features": [{"type": "Feature", "id": "http://data.archaeology.link/data/samian/loc_ds_1002066", "name": "Gro\u00df-Gerau", "dateprops": [], "properties": {"http://archaeology.link/ontology#exactMatch": ["http://www.wikidata.org/entity/Q103162984"], "http://archaeology.link/ontology#hasType": ["http://archaeology.link/ontology#DiscoverySite"], "http://purl.org/dc/elements/1.1/identifier": ["1002066"], "http://www.opengis.net/ont/geosparql#hasGeometry": ["http://data.archaeology.link/data/samian/loc_ds_1002066_geom"], "http://www.w3.org/1999/02/22-rdf-syntax-ns#type": ["http://archaeology.link/ontology#Location", "http://archaeology.link/ontology#DiscoverySite"], "http://www.w3.org/2000/01/rdf-schema#label": ["Gro\u00df-Gerau"], "http://www.w3.org/ns/prov-o/wasAttributedTo": ["http://data.archaeology.link/data/samian/ImportPythonScript_Samian"], "http://www.w3.org/ns/prov-o/wasDerivedFrom": ["http://www.wikidata.org/entity/Q90412636"], "http://www.w3.org/ns/prov-o/wasGeneratedBy": ["http://data.archaeology.link/data/samian/activity_loc_ds_1002066"]}, "geometry": {"type": "Point", "coordinates": [8.493610999999998, 49.923889], "crs": "4326"}}], "numberMatched": 1, "numberReturned": 1, "bbox": [8.493610999999998, 49.923889, 8.493610999999998, 49.923889], "crs": "http://www.opengis.net/def/crs/EPSG/0/4326"}