{"type": "FeatureCollection", "id": "http://www.wikidata.org/entity/Q103160839", "name": "Q103160839", "features": [{"type": "Feature", "id": "http://data.archaeology.link/data/samian/loc_ds_1000545", "name": "Drax", "dateprops": [], "properties": {"http://archaeology.link/ontology#exactMatch": ["http://www.wikidata.org/entity/Q103160839"], "http://archaeology.link/ontology#hasType": ["http://archaeology.link/ontology#DiscoverySite"], "http://purl.org/dc/elements/1.1/identifier": ["1000545"], "http://www.opengis.net/ont/geosparql#hasGeometry": ["http://data.archaeology.link/data/samian/loc_ds_1000545_geom"], "http://www.w3.org/1999/02/22-rdf-syntax-ns#type": ["http://archaeology.link/ontology#Location", "http://archaeology.link/ontology#DiscoverySite"], "http://www.w3.org/2000/01/rdf-schema#label": ["Drax"], "http://www.w3.org/ns/prov-o/wasAttributedTo": ["http://data.archaeology.link/data/samian/ImportPythonScript_Samian"], "http://www.w3.org/ns/prov-o/wasDerivedFrom": ["http://www.wikidata.org/entity/Q90412636"], "http://www.w3.org/ns/prov-o/wasGeneratedBy": ["http://data.archaeology.link/data/samian/activity_loc_ds_1000545"]}, "geometry": {"type": "Point", "coordinates": [-0.9808730000000002, 53.728404], "crs": "4326"}}], "numberMatched": 1, "numberReturned": 1, "bbox": [-0.9808730000000002, 53.728404, -0.9808730000000002, 53.728404], "crs": "http://www.opengis.net/def/crs/EPSG/0/4326"}