{"type": "FeatureCollection", "id": "http://www.wikidata.org/entity/Q103135828", "name": "Q103135828", "features": [{"type": "Feature", "id": "http://data.archaeology.link/data/samian/loc_pc_2000073", "name": "Manjarr\u00e9s", "dateprops": [], "properties": {"http://academic-meta-tool.xyz/vocab#instanceOf": ["http://archaeology.link/ontology#Location"], "http://archaeology.link/ontology#exactMatch": ["http://www.wikidata.org/entity/Q103135828"], "http://archaeology.link/ontology#hasType": ["http://archaeology.link/ontology#ProductionCentre"], "http://purl.org/dc/elements/1.1/identifier": ["2000073"], "http://www.opengis.net/ont/geosparql#hasGeometry": ["http://data.archaeology.link/data/samian/loc_pc_2000073_geom"], "http://www.w3.org/1999/02/22-rdf-syntax-ns#type": ["http://archaeology.link/ontology#Location", "http://archaeology.link/ontology#ProductionCentre"], "http://www.w3.org/2000/01/rdf-schema#label": ["Manjarr\u00e9s"], "http://www.w3.org/ns/prov-o/wasAttributedTo": ["http://data.archaeology.link/data/samian/ImportPythonScript_Samian"], "http://www.w3.org/ns/prov-o/wasDerivedFrom": ["http://www.wikidata.org/entity/Q90412636"], "http://www.w3.org/ns/prov-o/wasGeneratedBy": ["http://data.archaeology.link/data/samian/activity_loc_pc_2000073"]}, "geometry": {"type": "Point", "coordinates": [-2.6666701, 42.3833008], "crs": "4326"}}], "numberMatched": 1, "numberReturned": 1, "bbox": [-2.6666701, 42.3833008, -2.6666701, 42.3833008], "crs": "http://www.opengis.net/def/crs/EPSG/0/4326"}