{"type": "FeatureCollection", "id": "http://www.wikidata.org/entity/Q103160436", "name": "Q103160436", "features": [{"type": "Feature", "id": "http://data.archaeology.link/data/samian/loc_ds_1003597", "name": "Daspich-Ebange", "dateprops": [], "properties": {"http://archaeology.link/ontology#exactMatch": ["http://www.wikidata.org/entity/Q103160436"], "http://archaeology.link/ontology#hasType": ["http://archaeology.link/ontology#DiscoverySite"], "http://purl.org/dc/elements/1.1/identifier": ["1003597"], "http://www.opengis.net/ont/geosparql#hasGeometry": ["http://data.archaeology.link/data/samian/loc_ds_1003597_geom"], "http://www.w3.org/1999/02/22-rdf-syntax-ns#type": ["http://archaeology.link/ontology#Location", "http://archaeology.link/ontology#DiscoverySite"], "http://www.w3.org/2000/01/rdf-schema#label": ["Daspich-Ebange"], "http://www.w3.org/ns/prov-o/wasAttributedTo": ["http://data.archaeology.link/data/samian/ImportPythonScript_Samian"], "http://www.w3.org/ns/prov-o/wasDerivedFrom": ["http://www.wikidata.org/entity/Q90412636"], "http://www.w3.org/ns/prov-o/wasGeneratedBy": ["http://data.archaeology.link/data/samian/activity_loc_ds_1003597"]}, "geometry": {"type": "Point", "coordinates": [6.146389, 49.311943], "crs": "4326"}}], "numberMatched": 1, "numberReturned": 1, "bbox": [6.146389, 49.311943, 6.146389, 49.311943], "crs": "http://www.opengis.net/def/crs/EPSG/0/4326"}