{"type": "FeatureCollection", "id": "http://www.wikidata.org/entity/Q103158323", "name": "Q103158323", "features": [{"type": "Feature", "id": "http://data.archaeology.link/data/samian/loc_ds_1002303", "name": "Caistor-by-Norwich", "dateprops": [], "properties": {"http://archaeology.link/ontology#exactMatch": ["http://www.wikidata.org/entity/Q103158323"], "http://archaeology.link/ontology#hasType": ["http://archaeology.link/ontology#DiscoverySite"], "http://archaeology.link/ontology#pleiadesID": ["79735.0", "http://pleiades.stoa.org/places/79735.0"], "http://purl.org/dc/elements/1.1/identifier": ["1002303"], "http://purl.org/dc/terms/subject": ["samian ware discovery site"], "http://purl.org/dc/terms/title": ["Caistor-by-Norwich"], "http://www.opengis.net/ont/geosparql#hasGeometry": ["http://data.archaeology.link/data/samian/loc_ds_1002303_geom"], "http://www.w3.org/1999/02/22-rdf-syntax-ns#type": ["http://archaeology.link/ontology#Location", "http://archaeology.link/ontology#DiscoverySite", "http://pelagios.github.io/vocab/terms#AnnotatedThing"], "http://www.w3.org/2000/01/rdf-schema#label": ["Caistor-by-Norwich"], "http://www.w3.org/ns/prov-o/wasAttributedTo": ["http://data.archaeology.link/data/samian/ImportPythonScript_Samian"], "http://www.w3.org/ns/prov-o/wasDerivedFrom": ["http://www.wikidata.org/entity/Q90412636"], "http://www.w3.org/ns/prov-o/wasGeneratedBy": ["http://data.archaeology.link/data/samian/activity_loc_ds_1002303"], "http://xmlns.com/foaf/0.1/homepage": ["<http://lod.archaeology.link/samian/>"]}, "geometry": {"type": "Point", "coordinates": [1.291995, 52.582241], "crs": "4326"}}], "numberMatched": 1, "numberReturned": 1, "bbox": [1.291995, 52.582241, 1.291995, 52.582241], "crs": "http://www.opengis.net/def/crs/EPSG/0/4326"}